LICENSE
MANIFEST.in
README.md
setup.py
cpp/pylanczos.cpp
external/lambda-lanczos/include/lambda_lanczos/eigenpair_manager.hpp
external/lambda-lanczos/include/lambda_lanczos/exponentiator.hpp
external/lambda-lanczos/include/lambda_lanczos/lambda_lanczos.hpp
external/lambda-lanczos/include/lambda_lanczos/lambda_lanczos_tridiagonal.hpp
external/lambda-lanczos/include/lambda_lanczos/lambda_lanczos_tridiagonal_impl.hpp
external/lambda-lanczos/include/lambda_lanczos/lambda_lanczos_tridiagonal_lapack.hpp
external/lambda-lanczos/include/lambda_lanczos/lambda_lanczos_util.hpp
external/lambda-lanczos/include/lambda_lanczos/macro.hpp
external/lambda-lanczos/include/lambda_lanczos/util/common.hpp
external/lambda-lanczos/include/lambda_lanczos/util/linear_algebra.hpp
external/lambda-lanczos/include/lambda_lanczos/util/linear_algebra_lapack.hpp
include/pylanczos.hpp
pylanczos/__init__.py
pylanczos/pylanczos.py
pylanczos/pylanczos_exception.py
pylanczos.egg-info/PKG-INFO
pylanczos.egg-info/SOURCES.txt
pylanczos.egg-info/dependency_links.txt
pylanczos.egg-info/not-zip-safe
pylanczos.egg-info/requires.txt
pylanczos.egg-info/top_level.txt
test/test_exponentiator.py
test/test_pylanczos.py