Metadata-Version: 2.1
Name: pylanczos
Version: 2.1.1
Summary: Lanczos diagonalization library: Python interface with C++ implementation
Home-page: https://github.com/mrcdr/pylanczos
Author: mrcdr
License: MIT
License-File: LICENSE
